{
    "success": true,
    "rows": [
        {
            "year": 2019,
            "month": 1,
            "datetime": "2019-01-15T00:19:50+00:00",
            "section": "U.S.",
            "subsection": "Politics",
            "headline": "Republicans voted Monday night to remove Mr. King from the House Judiciary and Agriculture committees after he made remarks questioning why white supremacy is considered offensive.",
            "description": "House Republican leaders removed Representative Steve King of Iowa from the Judiciary and Agriculture Committees on Monday night as party officials scrambled to appear tough on racism and contain damage from comments Mr. King made to The New York Times questioning why white supremacy is considered offensive.",
            "location": "Iowa",
            "webURL": "https://www.nytimes.com/2019/01/14/us/politics/steve-king-white-supremacy.html",
            "imageURL": "https://www.nytimes.com/images/2019/01/15/us/politics/15kingrepubs-print-promo/15kingrepubs-print-promo-articleLarge-v2.jpg"
        },
        {
            "year": 2019,
            "month": 1,
            "datetime": "2019-01-15T01:05:52+00:00",
            "section": "U.S.",
            "subsection": "Politics",
            "headline": "The president\u2019s tweet about Ms. Warren referenced the location of one of the deadliest attacks on Native American people by the United States military.",
            "description": "It\u2019s been more than a century since the Wounded Knee massacre and the Battle of Little Bighorn, but both of these notorious conflicts were thrust into a national conversation about Native Americans and race following President Trump\u2019s Sunday night tweet directed at Senator Elizabeth Warren.",
            "location": "Wounded Knee (SD)",
            "webURL": "https://www.nytimes.com/2019/01/14/us/politics/wounded-knee-trump-warren.html",
            "imageURL": "https://www.nytimes.com/images/2019/01/15/us/politics/15xp-woundedknee2/merlin_149160660_1a719332-b43d-4ecb-9369-cd0f762f0191-articleLarge.jpg"
        },
        {
            "year": 2019,
            "month": 1,
            "datetime": "2019-01-15T01:12:55+00:00",
            "section": "New York",
            "subsection": "null",
            "headline": "A judge rejected the argument used by the New York Police Department when it refused to turn over records about its surveillance methods.",
            "description": "[What you need to know to start the day: Get New York Today in your inbox.]",
            "location": "New York City",
            "webURL": "https://www.nytimes.com/2019/01/14/nyregion/nypd-black-lives-matter-surveillance.html",
            "imageURL": "https://www.nytimes.com/images/2019/01/15/nyregion/15blm/merlin_89756836_8e8db24e-463b-4b3a-8ff4-f4a736f66339-articleLarge.jpg"
        },
        {
            "year": 2019,
            "month": 1,
            "datetime": "2019-01-15T02:13:54+00:00",
            "section": "U.S.",
            "subsection": "Politics",
            "headline": "New details of spending on President Trump\u2019s inaugural two years ago show that it roughly doubled that of his immediate predecessors.",
            "description": "WASHINGTON \u2014 Private donors put up $107 million to usher Donald J. Trump into office in style two years ago, and it is now clear just how enthusiastically his inaugural committee went to town with it.",
            "location": "Washington (DC)",
            "webURL": "https://www.nytimes.com/2019/01/14/us/politics/trump-inauguration-spending.html",
            "imageURL": "https://www.nytimes.com/images/2019/01/15/us/15dc-inaugural-1sub/merlin_149176377_b50351be-65e1-408f-a113-772ef12f9d93-articleLarge.jpg"
        },
        {
            "year": 2019,
            "month": 1,
            "datetime": "2019-01-15T02:48:27+00:00",
            "section": "Opinion",
            "subsection": "null",
            "headline": "President Recep Tayyip Erdogan of Turkey should look at the silver lining.",
            "description": "",
            "location": "Turkey",
            "webURL": "https://www.nytimes.com/2019/01/14/opinion/trump-turkey-tweet.html",
            "imageURL": "https://www.nytimes.com/images/2019/01/14/opinion/14chappatte/14chappatte-articleLarge.jpg"
        },
        {
            "year": 2019,
            "month": 1,
            "datetime": "2019-01-15T03:18:08+00:00",
            "section": "World",
            "subsection": "Asia Pacific",
            "headline": "The case of the blogger behind the popular website 64 Tianwang has drawn intense international scrutiny, in part because he has a kidney disease.",
            "description": "BEIJING \u2014 One of China\u2019s most prominent human rights activists, the blogger Huang Qi, went on trial on Monday on charges of leaking state secrets, and American diplomats seeking to attend the proceedings said they had been denied access.",
            "location": "China",
            "webURL": "https://www.nytimes.com/2019/01/14/world/asia/china-trial-huang-qi.html",
            "imageURL": "https://www.nytimes.com/images/2019/01/15/world/15China-dissident/merlin_138643980_0043ace0-24e8-4f52-96a5-85cd831433eb-articleLarge.jpg"
        },
        {
            "year": 2019,
            "month": 1,
            "datetime": "2019-01-15T04:44:40+00:00",
            "section": "U.S.",
            "subsection": "null",
            "headline": "The troops are expected to focus on \u201cmobile surveillance detection\u201d and placing concertina wire \u201cbetween ports of entry.\u201d",
            "description": "The deployment of active-duty United States troops at the border with Mexico will most likely be extended through September, the Pentagon said Monday.",
            "location": "United States",
            "webURL": "https://www.nytimes.com/2019/01/14/us/troops-border-wall.html",
            "imageURL": "https://www.nytimes.com/images/2019/01/15/us/15xp-bordertroops1/15xp-bordertroops1-articleLarge.jpg"
        },
        {
            "year": 2019,
            "month": 1,
            "datetime": "2019-01-15T07:30:05+00:00",
            "section": "Science",
            "subsection": "null",
            "headline": "Military analysts are increasingly concerned about the nation\u2019s \u201cadvanced, underestimated and highly lethal\u201d bioweapons program.",
            "description": "WASHINGTON \u2014 Pound for pound, the deadliest arms of all time are not nuclear but biological. A single gallon of anthrax, if suitably distributed, could end human life on Earth.",
            "location": "North Korea",
            "webURL": "https://www.nytimes.com/2019/01/15/science/north-korea-biological-weapons.html",
            "imageURL": "https://www.nytimes.com/images/2019/01/15/science/00NKBIO1/00NKBIO1-articleLarge.jpg"
        },
        {
            "year": 2019,
            "month": 1,
            "datetime": "2019-01-15T08:00:04+00:00",
            "section": "New York",
            "subsection": "null",
            "headline": "Gov. Andrew M. Cuomo said he will push to eliminate single-use plastic bags in the state. But so far, there are scant details about his plan. ",
            "description": "[What you need to know to start the day: Get New York Today in your inbox.]",
            "location": "New York State",
            "webURL": "https://www.nytimes.com/2019/01/15/nyregion/cuomo-plastic-bag-ban.html",
            "imageURL": "https://www.nytimes.com/images/2019/01/15/nyregion/15nyplasticbagban/merlin_137229834_f2051f9c-8d31-4b87-a18d-cde6d57e6996-articleLarge.jpg"
        },
        {
            "year": 2019,
            "month": 1,
            "datetime": "2019-01-15T10:00:10+00:00",
            "section": "New York",
            "subsection": "null",
            "headline": "The M.T.A. looked closely at the idea of hanging cables from the tunnel wall in 2014, but officials warned that it could damage the tube\u2019s lining.",
            "description": "[What you need to know to start the day: Get New York Today in your inbox.]",
            "location": "New York City",
            "webURL": "https://www.nytimes.com/2019/01/15/nyregion/l-train-mta-subway.html",
            "imageURL": "https://www.nytimes.com/images/2019/01/16/nyregion/16subway-promo/16subway-promo-articleLarge-v2.jpg"
        },
        {
            "year": 2019,
            "month": 1,
            "datetime": "2019-01-15T10:00:27+00:00",
            "section": "Real Estate",
            "subsection": "null",
            "headline": "From the street, the Seattle house is French Norman style; from the backyard, it\u2019s a modernist showplace.",
            "description": "From the street, the Seattle house is French Norman style; from the backyard, it\u2019s a modernist showplace.",
            "location": "Seattle (Wash)",
            "webURL": "https://www.nytimes.com/slideshow/2019/01/15/realestate/a-turret-in-front-a-glass-box-in-back.html",
            "imageURL": "https://www.nytimes.com/images/2019/01/20/realestate/20LOCATION-SEATTLE-slide-0L8E/00LOCATION-SEATTLE-slide-0L8E-articleLarge.jpg"
        },
        {
            "year": 2019,
            "month": 1,
            "datetime": "2019-01-15T10:01:29+00:00",
            "section": "Real Estate",
            "subsection": "null",
            "headline": "From the street, the house is French Norman style, with a turret; in back, it\u2019s a modernist showplace.",
            "description": "When Bob Boyce and Victor Ren first saw their home in the Capitol Hill neighborhood of Seattle, \u201cit was not the kind of house we were looking for,\u201d said Mr. Boyce, 48.",
            "location": "Seattle (Wash)",
            "webURL": "https://www.nytimes.com/2019/01/15/realestate/split-personality-in-seattle.html",
            "imageURL": "https://www.nytimes.com/images/2019/01/20/realestate/00LOCATION-SEATTLE-slide-KP57/00LOCATION-SEATTLE-slide-KP57-articleLarge.jpg"
        },
        {
            "year": 2019,
            "month": 1,
            "datetime": "2019-01-15T10:29:16+00:00",
            "section": "World",
            "subsection": "Middle East",
            "headline": "The Trump administration had condemned the endeavor as a pretext for testing technologies that could be transferred to ballistic missiles.",
            "description": "TEHRAN \u2014 Iranian officials said on Tuesday that a satellite launch that had been condemned by the Trump administration failed when the carrier rocket could not reach orbit.",
            "location": "Tehran (Iran)",
            "webURL": "https://www.nytimes.com/2019/01/15/world/middleeast/iran-satellite-launch-fail.html",
            "imageURL": "https://www.nytimes.com/images/2019/01/16/world/16iran/merlin_149199594_81e03adb-bc8a-4a39-8229-7398824e3d1e-articleLarge.jpg"
        },
        {
            "year": 2019,
            "month": 1,
            "datetime": "2019-01-15T10:42:26+00:00",
            "section": "New York",
            "subsection": "New York Today",
            "headline": "They didn\u2019t think it was safe enough. Or reliable enough. Now, M.T.A. officials are being asked to consider a similar plan.",
            "description": " [Want to get New York Today by email? Here's the sign-up.]",
            "location": "New York City",
            "webURL": "https://www.nytimes.com/2019/01/15/nyregion/newyorktoday/new-york-news-l-train-sully.html",
            "imageURL": "https://www.nytimes.com/images/2019/01/15/nyregion/15nytoday1/merlin_148714722_de30854a-aae1-4e9f-8f7a-3bdd513aec45-articleLarge.jpg"
        },
        {
            "year": 2019,
            "month": 1,
            "datetime": "2019-01-15T10:50:27+00:00",
            "section": "World",
            "subsection": "Europe",
            "headline": "After two and a half years of argument, Parliament finally had its say on a bill on Britain\u2019s departure from the E.U., and soundly rejected the prime minister\u2019s deal.",
            "description": "",
            "location": "Great Britain",
            "webURL": "https://www.nytimes.com/2019/01/15/world/europe/brexit-vote.html",
            "imageURL": "null"
        },
        {
            "year": 2019,
            "month": 1,
            "datetime": "2019-01-15T11:00:03+00:00",
            "section": "Opinion",
            "subsection": "null",
            "headline": "By any reasonable metric, \u201cmass\u201d immigration is a myth. The reality is that America desperately needs to pick up the pace of immigration for its economic health.",
            "description": "President Trump has shut down the government to get money for a border wall that he says will stop illegal immigration. But the fact of the matter is that that\u2019s not all he wants to stop. During the three-day shutdown last January, he demanded a 40 percent reduction in legal immigration, arguing that America has been swamped by immigrants. ",
            "location": "United States",
            "webURL": "https://www.nytimes.com/2019/01/15/opinion/trump-immigration-myth.html",
            "imageURL": "https://www.nytimes.com/images/2019/01/14/opinion/14DALMIA/merlin_148331961_f90bce52-f9fb-4225-abf7-4d94e9cdfc72-articleLarge.jpg"
        },
        {
            "year": 2019,
            "month": 1,
            "datetime": "2019-01-15T11:42:15+00:00",
            "section": "World",
            "subsection": "Africa",
            "headline": "Mr. Gbagbo is the first former head of state to be tried at the International Criminal Court in The Hague.",
            "description": "DAKAR, Senegal \u2014 The International Criminal Court in The Hague said on Tuesday that it had acquitted the former president of Ivory Coast, Laurent Gbagbo, and one of his aides of crimes against humanity and a litany of other charges related to months of violence that followed the country\u2019s presidential election in 2010.",
            "location": "Ivory Coast",
            "webURL": "https://www.nytimes.com/2019/01/15/world/africa/laurent-gbagbo-ivory-coast-icc.html",
            "imageURL": "https://www.nytimes.com/images/2019/01/16/world/16ICC-print/merlin_149204589_889db9cf-7e3a-4da0-81c5-7eb163ae65c9-articleLarge.jpg"
        },
        {
            "year": 2019,
            "month": 1,
            "datetime": "2019-01-15T13:31:25+00:00",
            "section": "Opinion",
            "subsection": "null",
            "headline": "How a numbers problem helped create the Brexit mess.",
            "description": "This article is part of David Leonhardt\u2019s newsletter. You can sign up here to receive it each weekday.",
            "location": "Great Britain",
            "webURL": "https://www.nytimes.com/2019/01/15/opinion/brexit-vote-theresa-may-referendum.html",
            "imageURL": "https://www.nytimes.com/images/2019/01/15/opinion/15leonhardt-newsletter/merlin_149207115_2d9c3d18-a095-4601-80df-cafb0be051c9-articleLarge.jpg"
        },
        {
            "year": 2019,
            "month": 1,
            "datetime": "2019-01-15T13:43:52+00:00",
            "section": "Technology",
            "subsection": "null",
            "headline": "Ren Zhengfei, C.E.O. of the Chinese tech giant, said he would wait to see if President Trump intervened in the case of his daughter, who is accused of fraud.",
            "description": "BEIJING \u2014 To entrepreneurs in China, he is a legend akin to Steve Jobs.",
            "location": "China",
            "webURL": "https://www.nytimes.com/2019/01/15/technology/huawei-ren-zhengfei.html",
            "imageURL": "https://www.nytimes.com/images/2019/01/16/business/16ren/16ren-articleLarge.jpg"
        },
        {
            "year": 2019,
            "month": 1,
            "datetime": "2019-01-15T13:46:45+00:00",
            "section": "World",
            "subsection": "Africa",
            "headline": "The Shabab group, which has ties to Al Qaeda, struck a luxury hotel and an office complex in Kenya\u2019s capital.",
            "description": "Assailants identified as Shabab militants attacked a Nairobi luxury hotel and office complex on Tuesday, spreading death and panic as the police in Kenya\u2019s capital evacuated civilians and sealed off the area.",
            "location": "Nairobi (Kenya)",
            "webURL": "https://www.nytimes.com/2019/01/15/world/africa/nairobi-attack.html",
            "imageURL": "https://www.nytimes.com/images/2019/01/16/world/16nairobi-1-print/merlin_149213556_d892fa4e-9729-401b-be38-6a7e76e63b56-articleLarge.jpg"
        }
    ]
}